{"cameraMode":{"drawMode":0,"name":"Shaded","section":"Shading Mode"},"sceneLighting":true,"audioPlay":false,"sceneViewState":{"showFog":true,"showMaterialUpdate":false,"showSkybox":true,"showFlares":true,"showImageEffects":true,"showParticleSystems":true},"in2DMode":false,"pivot":{"x":-0.15826864540576936,"y":0.028277873992919923,"z":5.158407688140869},"rotation":{"x":-0.205821692943573,"y":-0.011156212538480759,"z":0.002354272874072194,"w":-0.9785559773445129},"size":6.53148889541626,"orthographic":false}